svg2gcode/__init__.py
svg2gcode/__main__.py
svg2gcode/svg_to_gcode/LICENSE
svg2gcode/svg_to_gcode/__init__.py
svg2gcode/svg_to_gcode/css_color.py
svg2gcode/svg_to_gcode/formulas.py
svg2gcode/svg_to_gcode/compiler/__init__.py
svg2gcode/svg_to_gcode/compiler/_compiler.py
svg2gcode/svg_to_gcode/compiler/interfaces/__init__.py
svg2gcode/svg_to_gcode/compiler/interfaces/_abstract_interface.py
svg2gcode/svg_to_gcode/compiler/interfaces/_fan_controlled_gcode.py
svg2gcode/svg_to_gcode/compiler/interfaces/_gcode.py
svg2gcode/svg_to_gcode/geometry/__init__.py
svg2gcode/svg_to_gcode/geometry/_abstract_chain.py
svg2gcode/svg_to_gcode/geometry/_abstract_curve.py
svg2gcode/svg_to_gcode/geometry/_circular_arc.py
svg2gcode/svg_to_gcode/geometry/_cubic_bazier.py
svg2gcode/svg_to_gcode/geometry/_elliptical_arc.py
svg2gcode/svg_to_gcode/geometry/_line.py
svg2gcode/svg_to_gcode/geometry/_line_segment_chain.py
svg2gcode/svg_to_gcode/geometry/_matrix.py
svg2gcode/svg_to_gcode/geometry/_quadratic_bazier.py
svg2gcode/svg_to_gcode/geometry/_raster_image.py
svg2gcode/svg_to_gcode/geometry/_smooth_arc_chain.py
svg2gcode/svg_to_gcode/geometry/_vector.py
svg2gcode/svg_to_gcode/svg_parser/__init__.py
svg2gcode/svg_to_gcode/svg_parser/_parser_methods.py
svg2gcode/svg_to_gcode/svg_parser/_path.py
svg2gcode/svg_to_gcode/svg_parser/_transformation.py
svg2gcode/svg_to_gcode/svg_parser/debug_methods.py
svg2gcode-3.3.7.dist-info/entry_points.txt
svg2gcode-3.3.7.dist-info/licenses/LICENSE
svg2gcode-3.3.7.dist-info/WHEEL
svg2gcode-3.3.7.dist-info/METADATA
svg2gcode-3.3.7.dist-info/RECORD
