Metadata-Version: 2.4
Name: svg2gcode
Version: 3.3.7
Summary: svg2gcode: convert an SVG (Scalable Vector Graphic) image to gcode.
Keywords: scalable vector graphics,svg,image,laser cutter,laser engraving
Author-email: Johannes Noordanus <mailjohannes.mailnoordanus@gmail.com>
Requires-Python: >=3.11
Classifier: License :: OSI Approved :: MIT License
License-File: LICENSE
Requires-Dist: numpy >= 1.24.3
Requires-Dist: Pillow >= 9.5.0
Requires-Dist: image2gcode >= 2.9.8
Project-URL: Home, https://github.com/johannesnoordanus/svg2gcode
